opentelemetry_resourcedetector_docker/__init__.py
opentelemetry_resourcedetector_docker/py.typed
opentelemetry_resourcedetector_docker-0.4.0.dist-info/LICENSE
opentelemetry_resourcedetector_docker-0.4.0.dist-info/METADATA
opentelemetry_resourcedetector_docker-0.4.0.dist-info/WHEEL
opentelemetry_resourcedetector_docker-0.4.0.dist-info/top_level.txt
opentelemetry_resourcedetector_docker-0.4.0.dist-info/RECORD
