Metadata-Version: 2.1
Name: opentelemetry-resourcedetector-docker
Version: 0.4.0
Summary: An OpenTelemetry package to populates Resource attributes from Docker containers
Home-page: https://github.com/chrisguidry/opentelemetry-resourcedetector-docker
Author: Chris Guidry
Author-email: chris@theguidrys.us
Project-URL: Bug Tracker, https://github.com/chrisguidry/opentelemetry-resourcedetector-docker/issues
Classifier: Programming Language :: Python :: 3
Classifier: License :: OSI Approved :: MIT License
Requires-Python: >=3.8
Provides-Extra: dev
License-File: LICENSE
